[
	{
		"__TYPE__": "SharedSliceContent",
		"variation": "default",
		"primary": {
			"author": {
				"__TYPE__": "LinkContent",
				"value": {
					"__TYPE__": "DocumentLink",
					"id": "mock_document_id"
				}
			},
			"photographer": {
				"__TYPE__": "LinkContent",
				"value": {
					"__TYPE__": "DocumentLink",
					"id": "mock_document_id"
				}
			},
			"official_photos": {
				"__TYPE__": "BooleanContent",
				"value": false
			},
			"translator_en": {
				"__TYPE__": "LinkContent",
				"value": {
					"__TYPE__": "DocumentLink",
					"id": "mock_document_id"
				}
			},
			"translator_jp": {
				"__TYPE__": "LinkContent",
				"value": {
					"__TYPE__": "DocumentLink",
					"id": "mock_document_id"
				}
			},
			"translator_fr": {
				"__TYPE__": "LinkContent",
				"value": {
					"__TYPE__": "DocumentLink",
					"id": "mock_document_id"
				}
			},
			"photographer_2": {
				"__TYPE__": "LinkContent",
				"value": {
					"__TYPE__": "DocumentLink",
					"id": "mock_document_id"
				}
			}
		},
		"items": []
	}
]